trattoria_core-0.4.6.dist-info/METADATA
trattoria_core-0.4.6.dist-info/WHEEL
trattoria_core/__init__.py
trattoria_core/trattoria_core.cpython-38-darwin.so
trattoria_core-0.4.6.dist-info/RECORD
